kokojson/__init__.py
kokojson/main.py
kokojson-0.1.5.dist-info/METADATA
kokojson-0.1.5.dist-info/WHEEL
kokojson-0.1.5.dist-info/top_level.txt
kokojson-0.1.5.dist-info/RECORD
