Metadata-Version: 2.1
Name: kokojson
Version: 0.1.5
Summary: A module for safe JSON handling in Python
Home-page: https://github.com/your_username/kokojson
Author: kokofixcomputers
Author-email: kokocanfixit@kokofixcomputers.serv00.net
License: UNKNOWN
Platform: UNKNOWN
Classifier: Development Status :: 3 - Alpha
Classifier: Intended Audience :: Developers
Classifier: License :: OSI Approved :: MIT License
Classifier: Programming Language :: Python :: 3
Classifier: Programming Language :: Python :: 3.6
Classifier: Programming Language :: Python :: 3.7
Classifier: Programming Language :: Python :: 3.8
Classifier: Programming Language :: Python :: 3.9
Classifier: Operating System :: OS Independent
Requires-Python: >=3.6
